verbex/__init__.py
verbex/py.typed
verbex/verbex.py
Verbex-2.0.2.dist-info/LICENSE.txt
Verbex-2.0.2.dist-info/METADATA
Verbex-2.0.2.dist-info/WHEEL
Verbex-2.0.2.dist-info/top_level.txt
Verbex-2.0.2.dist-info/RECORD
