Metadata-Version: 2.1
Name: Verbex
Version: 2.0.2
Summary: Python verbal based regular expressions
Author: R.Broderick
Project-URL: homepage, https://github.com/rbroderi/Verbex
Project-URL: documentation, https://rbroderi.github.io/Verbex/
Classifier: License :: OSI Approved :: GNU General Public License v3 or later (GPLv3+)
Classifier: Programming Language :: Python :: 3
Classifier: Programming Language :: Python :: 3.10
Classifier: Programming Language :: Python :: 3.11
Classifier: Programming Language :: Python :: 3.12
Requires-Python: >=3.10.0
License-File: LICENSE.txt
Requires-Dist: beartype
Requires-Dist: typing-extensions ; python_version < "3.12"
Provides-Extra: dev
Requires-Dist: build ; extra == 'dev'
Requires-Dist: dapperdata ; extra == 'dev'
Requires-Dist: glom ; extra == 'dev'
Requires-Dist: mypy ; extra == 'dev'
Requires-Dist: pytest ; extra == 'dev'
Requires-Dist: pytest-cov ; extra == 'dev'
Requires-Dist: pytest-pretty ; extra == 'dev'
Requires-Dist: ruamel.yaml ; extra == 'dev'
Requires-Dist: ruff ; extra == 'dev'
Requires-Dist: toml-sort ; extra == 'dev'
Requires-Dist: uv ; extra == 'dev'
Requires-Dist: validate-pyproject ; extra == 'dev'
Requires-Dist: packaging ; extra == 'dev'
Requires-Dist: snakeviz ; extra == 'dev'
Requires-Dist: pre-commit ; extra == 'dev'
Requires-Dist: tox ; extra == 'dev'
Requires-Dist: tox-pyenv-redux ; extra == 'dev'
Requires-Dist: pylint ; extra == 'dev'
Requires-Dist: perflint ; extra == 'dev'
Requires-Dist: pip-audit ; extra == 'dev'
Provides-Extra: docs
Requires-Dist: Sphinx ; extra == 'docs'
Requires-Dist: sphinx-autodoc-typehints ; extra == 'docs'
Requires-Dist: sphinx-rtd-theme ; extra == 'docs'
Requires-Dist: sphinx-rtd-size ; extra == 'docs'
Requires-Dist: autodocsumm ; extra == 'docs'
Requires-Dist: sphinx-pyproject ; extra == 'docs'
Provides-Extra: optional
